m4b_util/__init__.py
m4b_util/__main__.py
m4b_util/__version__.py
m4b_util/helpers/__init__.py
m4b_util/helpers/audiobook.py
m4b_util/helpers/cover_utils.py
m4b_util/helpers/ffmetadata.py
m4b_util/helpers/ffprobe.py
m4b_util/helpers/ffprogress.py
m4b_util/helpers/parallel_ffmpeg.py
m4b_util/helpers/segment_data.py
m4b_util/helpers/splitter.py
m4b_util/helpers/finders/__init__.py
m4b_util/helpers/finders/chapter_finder.py
m4b_util/helpers/finders/silence_finder.py
m4b_util/subcommands/__init__.py
m4b_util/subcommands/bind.py
m4b_util/subcommands/cover.py
m4b_util/subcommands/labels.py
m4b_util/subcommands/slide.py
m4b_util/subcommands/split.py
m4b_util-2025.4.16.dist-info/licenses/LICENSE.txt
m4b_util-2025.4.16.dist-info/METADATA
m4b_util-2025.4.16.dist-info/WHEEL
m4b_util-2025.4.16.dist-info/entry_points.txt
m4b_util-2025.4.16.dist-info/top_level.txt
m4b_util-2025.4.16.dist-info/RECORD
