Metadata-Version: 2.4
Name: m4b_util
Version: 2025.4.16
Summary: A collection of command line utilities for creating, editing, and generally working with m4b files.
License: MIT License
Project-URL: repository, https://github.com/Tsubashi/m4b-util
Keywords: Audiobook,m4b
Classifier: Development Status :: 5 - Production/Stable
Classifier: Environment :: Console
Classifier: License :: OSI Approved :: MIT License
Requires-Python: >=3.8
License-File: LICENSE.txt
Requires-Dist: natsort~=8.2.0
Requires-Dist: rich~=12.6.0
Requires-Dist: lark~=1.2.2
Provides-Extra: test
Requires-Dist: pytest-cov; extra == "test"
Requires-Dist: flake8; extra == "test"
Requires-Dist: flake8-bugbear; extra == "test"
Requires-Dist: flake8-docstrings; extra == "test"
Requires-Dist: flake8-import-order; extra == "test"
Requires-Dist: flake8-colors; extra == "test"
Requires-Dist: pep8-naming; extra == "test"
Dynamic: license-file
